imgkit/__init__.py
imgkit/api.py
imgkit/config.py
imgkit/imgkit.py
imgkit/source.py
imgkit-1.2.2.dist-info/LICENSE
imgkit-1.2.2.dist-info/METADATA
imgkit-1.2.2.dist-info/WHEEL
imgkit-1.2.2.dist-info/top_level.txt
imgkit-1.2.2.dist-info/RECORD
