Metadata-Version: 2.1
Name: imgkit
Version: 1.2.2
Summary: Wkhtmltopdf python wrapper to convert html to image using the webkit rendering engine and qt
Home-page: https://github.com/jarrekk/imgkit
Author: Jarrekk
Author-email: me@jarrekk.com
License: UNKNOWN
Project-URL: Bug Tracker, https://github.com/jarrekk/imgkit/issues
Platform: UNKNOWN
Classifier: Programming Language :: Python
Classifier: Programming Language :: Python :: 2.7
Classifier: Programming Language :: Python :: 3.6
Classifier: Programming Language :: Python :: 3.7
Classifier: Programming Language :: Python :: 3.8
Classifier: Programming Language :: Python :: 3.9
Classifier: License :: OSI Approved :: MIT License
Classifier: Operating System :: OS Independent
Classifier: Topic :: Text Processing
Classifier: Topic :: Text Processing :: General
Classifier: Topic :: Text Processing :: Markup
Classifier: Topic :: Text Processing :: Markup :: HTML
Classifier: Topic :: Text Processing :: Markup :: XML
Classifier: Topic :: Utilities
